<?xml version = '1.0'  encoding = 'ISO-8859-1'  standalone = 'yes' ?>
<!-- PlotDigitizer data file: created on Wed Jul 27 14:59:16 CEST 2022 -->
<data>
<image file='data.png' />
<axesnames x='Temperature'  y='Depth' />
<calibpoints minXaxisX='194.0' minXaxisY='466.0' maxXaxisX='620.0' maxXaxisY='467.0' minYaxisX='193.5' minYaxisY='40.0' maxYaxisX='194.0' maxYaxisY='466.0' aX1='-20.0' aX2='-4.0' aY1='0.0' aY2='120.0' isXLog='false' isYLog='false' />
<point n='0' x='233.5' y='75.5' dx='-18.55086870512517' dy='9.973577700571145' />
<point n='1' x='239.0' y='111.5' dx='-18.341123117530046' dy='20.110813856415877' />
<point n='2' x='238.5' y='146.5' dx='-18.35681656628664' dy='29.970326573008464' />
<point n='3' x='241.5' y='164.5' dx='-18.242554152867857' dy='35.03877933935985' />
<point n='4' x='245.0' y='183.0' dx='-18.10946841748541' dy='40.247746941047126' />
<point n='5' x='247.0' y='201.0' dx='-18.032764482551507' dy='45.31686095368244' />
<point n='6' x='249.5' y='216.5' dx='-17.9375017219813' dy='49.68141705078646' />
<point n='7' x='252.0' y='235.0' dx='-17.84197446508373' dy='54.891045898757675' />
<point n='8' x='254.5' y='253.5' dx='-17.74644720818616' dy='60.10067474672888' />
<point n='9' x='257.0' y='270.0' dx='-17.651096282173498' dy='64.74692176078864' />
<point n='10' x='260.0' y='288.0' dx='-17.53683386875472' dy='69.81537452714002' />
<point n='11' x='263.0' y='306.5' dx='-17.42252737261471' dy='75.02467275196926' />
<point n='12' x='265.0' y='323.0' dx='-17.345955685844487' dy='79.67125038917098' />
<point n='13' x='268.0' y='341.5' dx='-17.23164918970448' dy='84.88054861400022' />
<point n='14' x='273.0' y='376.5' dx='-17.04077100679425' dy='94.73642447603117' />
<point n='15' x='281.5' y='409.5' dx='-16.718614480071857' dy='104.02660414215691' />
</data>
