<?xml version = '1.0'  encoding = 'ISO-8859-1'  standalone = 'yes' ?>
<!-- PlotDigitizer data file: created on Mon Aug 08 14:32:14 CEST 2022 -->
<data>
<image file='data.png' />
<axesnames x='Temperature'  y='Depth' />
<calibpoints minXaxisX='118.0' minXaxisY='82.0' maxXaxisX='708.0' maxXaxisY='82.0' minYaxisX='118.0' minYaxisY='82.0' maxYaxisX='117.0' maxYaxisY='914.0' aX1='-10.0' aX2='10.0' aY1='0.0' aY2='14.0' isXLog='false' isYLog='false' />
<point n='0' x='402.0' y='141.0' dx='-0.3728813559322042' dy='0.9927884615384615' />
<point n='1' x='398.0' y='203.0' dx='-0.5084745762711869' dy='2.0360576923076925' />
<point n='2' x='333.0' y='265.0' dx='-2.711864406779661' dy='3.0793269230769225' />
<point n='3' x='290.0' y='320.0' dx='-4.169491525423728' dy='4.004807692307692' />
<point n='4' x='266.0' y='379.0' dx='-4.983050847457626' dy='4.997596153846153' />
<point n='5' x='254.0' y='488.0' dx='-5.389830508474576' dy='6.831730769230769' />
<point n='6' x='257.0' y='556.0' dx='-5.288135593220339' dy='7.975961538461537' />
<point n='7' x='265.0' y='616.0' dx='-5.016949152542374' dy='8.985576923076923' />
<point n='8' x='266.0' y='679.0' dx='-4.983050847457626' dy='10.045673076923077' />
<point n='9' x='278.0' y='775.0' dx='-4.576271186440678' dy='11.661057692307692' />
<point n='10' x='286.0' y='856.0' dx='-4.305084745762711' dy='13.024038461538462' />
</data>
