<?xml version = '1.0'  encoding = 'ISO-8859-1'  standalone = 'yes' ?>
<!-- PlotDigitizer data file: created on Mon Aug 08 16:51:41 CEST 2022 -->
<data>
<image file='data.png' />
<axesnames x='Temperature'  y='Depth' />
<calibpoints minXaxisX='186.0' minXaxisY='126.0' maxXaxisX='249.0' maxXaxisY='127.0' minYaxisX='60.0' minYaxisY='129.0' maxYaxisX='59.666666666666664' maxYaxisY='524.3333333333334' aX1='-3.0' aX2='0.0' aY1='0.0' aY2='750.0' isXLog='false' isYLog='false' />
<point n='0' x='213.0' y='133.33333333333334' dx='-1.7090680100755673' dy='3.6135387250900237' />
<point n='1' x='225.0' y='137.33333333333334' dx='-1.1347607052896738' dy='10.840616175270071' />
<point n='2' x='230.66666666666666' y='140.0' dx='-0.8629722921914382' dy='15.728931061711222' />
<point n='3' x='237.33333333333334' y='142.33333333333334' dx='-0.5438287153652404' dy='19.95476384855263' />
<point n='4' x='242.0' y='145.0' dx='-0.3196473551637311' dy='24.87319155770288' />
<point n='5' x='238.66666666666666' y='150.66666666666666' dx='-0.4740554156171317' dy='35.723845340542624' />
<point n='6' x='238.66666666666666' y='156.0' dx='-0.4700251889168783' dy='45.84175377079461' />
<point n='7' x='217.33333333333334' y='167.33333333333334' dx='-1.4770780856423205' dy='67.98471606954055' />
<point n='8' x='189.66666666666666' y='185.0' dx='-2.780856423173807' dy='102.333409173035' />
</data>
